{"__type__":"cc.SpriteAtlas","_spriteFrames":{"bg_element_03":{"__uuid__":"55ibHwmQBNi7QY4CgT/5ht"},"bj_suanshibeij":{"__uuid__":"f0S9YEaIBNW4fQlHCCKuOb"},"an_zailaiyicibeij":{"__uuid__":"aaiDtmYaNDEbmJsrPMe/Rn"},"ss_chuhao":{"__uuid__":"b5dprEB3NL1ZW24N0MXxAQ"},"ss_chuhengx":{"__uuid__":"ff7HAyTGFIL5t+SPZ6codq"},"ss_hengxian":{"__uuid__":"f0dtOXofxHn7zhBqBT97Xs"},"xz_xuxian":{"__uuid__":"16JR/4Y55F0ou3N8p/ts5h"},"xz_xiaoshudian":{"__uuid__":"c4OK7D03VPBKdzA45Gw3VT"},"bj_tuan13":{"__uuid__":"f6SvKK8PVKE7FQw8Y0NixS"},"airship":{"__uuid__":"09KBeV08hEGIErCOrJocze"},"xz_wenzibj":{"__uuid__":"01twrMVuRMeZ21F3Og3bIc"},"xz_jiantou":{"__uuid__":"6eceRqs/VBpI9+EP+Gqjd2"},"ks_anniubeij":{"__uuid__":"f0h60KTlxIGoeG7JjmA75t"},"tip":{"__uuid__":"70L5SmvSFOQYmjShOWF4AV"},"bj_tuan01":{"__uuid__":"4e+qbQ7D1LC4FrrxNCRhIY"},"xz_shuidixia":{"__uuid__":"93uULBdt1AP5vkAKdOWGFn"},"xz_shuidi":{"__uuid__":"d6A6tDtn9AFaNs0vvuHfMH"},"dotbg":{"__uuid__":"6eQOp3R0hNILJk8bs5LoAk"},"ts_yingliangbeij":{"__uuid__":"47odfqAExKfri+mD7J4HGD"},"bj_tuan04":{"__uuid__":"51P3UKosNMirJX7cW1m/UF"},"bj_tuan09":{"__uuid__":"f3KssnEP9Erq1h0bBMyRIt"},"an_chongxinbof":{"__uuid__":"08rMa1eaxHEaicbgtNLRYl"},"laba":{"__uuid__":"34WrjQplZGhIympoUfU43r"},"bj_tuan03":{"__uuid__":"7fPXiyVWFB6rk09Sm7vubz"},"bj_tuan02":{"__uuid__":"a2qJThxQJGUJu2ojGxS9ND"},"ks_anniuzhongjian":{"__uuid__":"4bK1H6QvZDRZcURTA4Q5WA"},"bg_element_02":{"__uuid__":"e4l1NiVV9ArK4w99RVr/rW"},"tc_huojianbeij":{"__uuid__":"c1d39iOJ1NLLiQSOtdrPj5"},"bj_tuan14":{"__uuid__":"61KUmYqQZA6KtmUDZik31t"},"bj_tuan07":{"__uuid__":"b6AmTLXfVAE4sIXn70RRl8"},"circle":{"__uuid__":"ebnaZtXRVFOKU775IAVNxv"},"bj_tuan11":{"__uuid__":"0aPHCM801HqLgljt9Jb9pn"},"bj_tuan08":{"__uuid__":"e0889a1KBEmr+gA50ocYoa"},"bj_tuan12":{"__uuid__":"03pKVvq3hFY5Jf/781BeoM"},"bj_fanggedinbu":{"__uuid__":"bbvQYmwddJGZp+6DRoe/n+"},"bj_tuan06":{"__uuid__":"52k5I/RR9Pt7OiOE8+4ULY"},"sign_division":{"__uuid__":"d0I76z2AJMW63YKrrZFL12"},"dot_big":{"__uuid__":"f9TxhEbMVL0aeL4eM6edLI"},"bg_element_01":{"__uuid__":"5feH+IlQZCRZ0/dx1mqEb8"},"bj_tuan10":{"__uuid__":"41lNVZLJ5D3IdXtJly3pQi"},"ts_tishik":{"__uuid__":"0dNlEyQxJBSJWXGvomDoMT"},"xz_shuzibj":{"__uuid__":"407LTw79JP+6gLPe6DPq2o"},"bg_card":{"__uuid__":"57fAHV6gtJC4hPQpNeT0jf"},"bg_question":{"__uuid__":"1acPCtUlNNK78D/DLMs5/L"},"xz_denghao":{"__uuid__":"3eereeurZFqoXGJ1MBiwL/"},"xz_chenghao":{"__uuid__":"80oJ9K9TlHh6RAp9JdNIRU"},"bj_fanggezhongjian":{"__uuid__":"6cPS5N0N1CzImMXebW2FBO"},"dot_small":{"__uuid__":"e65BkdDs5AHLhXTz3P7tqJ"},"bj_fanggedibu":{"__uuid__":"83duQLpdJHjoeYUe/d4CvO"}}}